tests/test_client.py
vantage6/client/__build__
vantage6/client/__init__.py
vantage6/client/_version.py
vantage6/client/exceptions.py
vantage6/client/filter.py
vantage6/client/utils.py
vantage6/client/subclients/__init__.py
vantage6/client/subclients/study.py
vantage6/client/subclients/store/__init__.py
vantage6/client/subclients/store/algorithm.py
vantage6/client/subclients/store/algorithm_store.py
vantage6/client/subclients/store/policy.py
vantage6/client/subclients/store/review.py
vantage6/client/subclients/store/role.py
vantage6/client/subclients/store/rule.py
vantage6/client/subclients/store/user.py
vantage6_client_blob-4.10.2.dist-info/METADATA
vantage6_client_blob-4.10.2.dist-info/WHEEL
vantage6_client_blob-4.10.2.dist-info/top_level.txt
vantage6_client_blob-4.10.2.dist-info/RECORD
