Metadata-Version: 2.4
Name: vantage6_client-blob
Version: 4.10.2
Summary: Vantage6 client
Home-page: https://github.com/vantage6/vantage6
Requires-Python: >=3.10
Requires-Dist: PyJWT==2.6.0
Requires-Dist: pyfiglet==0.8.post1
Requires-Dist: vantage6-common-blob==4.10.2
Provides-Extra: dev
Requires-Dist: black; extra == "dev"
Requires-Dist: pre-commit; extra == "dev"
Dynamic: description
Dynamic: description-content-type
Dynamic: home-page
Dynamic: provides-extra
Dynamic: requires-dist
Dynamic: requires-python
Dynamic: summary
